bit_field/__init__.py
bit_field/__main__.py
bit_field/cli.py
bit_field/jsonml_stringify.py
bit_field/render.py
bit_field/tspan.py
bit_field-1.0.1.dist-info/LICENSE
bit_field-1.0.1.dist-info/LICENSE-ORIGINAL
bit_field-1.0.1.dist-info/METADATA
bit_field-1.0.1.dist-info/WHEEL
bit_field-1.0.1.dist-info/entry_points.txt
bit_field-1.0.1.dist-info/top_level.txt
bit_field-1.0.1.dist-info/RECORD
