Metadata-Version: 2.1
Name: bit-field
Version: 1.0.1
Summary: A bitfield diagram renderer
Home-page: https://github.com/Arth-ur/bitfield
Author: Arthur Gay
License: MIT
Keywords: bitfield,bytefield,diagram,renderer,svg
Classifier: Programming Language :: Python :: 3
Classifier: License :: OSI Approved :: MIT License
Classifier: Operating System :: OS Independent
License-File: LICENSE
License-File: LICENSE-ORIGINAL
Provides-Extra: json5
Requires-Dist: json5 (>=0.9.6) ; extra == 'json5'
